LICENSE
README.md
pyproject.toml
setup.py
hydamo_validation/__init__.py
hydamo_validation/datamodel.py
hydamo_validation/datasets.py
hydamo_validation/geometry.py
hydamo_validation/logical_validation.py
hydamo_validation/styles.py
hydamo_validation/summaries.py
hydamo_validation/syntax_validation.py
hydamo_validation/utils.py
hydamo_validation/validator.py
hydamo_validation.egg-info/PKG-INFO
hydamo_validation.egg-info/SOURCES.txt
hydamo_validation.egg-info/dependency_links.txt
hydamo_validation.egg-info/requires.txt
hydamo_validation.egg-info/top_level.txt
hydamo_validation.egg-info/zip-safe
hydamo_validation/functions/__init__.py
hydamo_validation/functions/general.py
hydamo_validation/functions/logic.py
hydamo_validation/functions/topologic.py
hydamo_validation/schemas/hydamo/HyDAMO_2.2.json
hydamo_validation/schemas/hydamo/HyDAMO_2.3.json
hydamo_validation/schemas/hydamo/HyDAMO_2.4.json
hydamo_validation/schemas/rules/rules_1.0.json
hydamo_validation/schemas/rules/rules_1.1.json
hydamo_validation/schemas/rules/rules_1.2.json
hydamo_validation/schemas/rules/rules_1.3.json
hydamo_validation/schemas/rules/rules_1.4.json
hydamo_validation/styles/hydroobject.qml
hydamo_validation/styles/hydroobject.sld
tests/test_datasets.py
tests/test_dommelerwaard.py
tests/test_general_functions.py
tests/test_hydamo_2_2.py
tests/test_hydamo_2_4.py
tests/test_init.py
tests/test_logic_functions.py
tests/test_not_overlapping.py
tests/test_productie.py
tests/test_structures_at_interersections.py
tests/test_summaries.py
tests/test_testset.py
tests/test_topologic_functions.py
tests/test_validationrules.py
tests/test_wrij.py
tests/test_wrij_profielen.py