Metadata-Version: 2.1
Name: hydamo_validation
Version: 1.4.1
Summary: Validation module for HyDAMO data
Author-email: Daniel Tollenaar <daniel@d2hydro.nl>
License: MIT
Project-URL: Source, https://github.com/HetWaterschapshuis/HyDAMOValidatieModule
Requires-Python: >=3.12
License-File: LICENSE
Requires-Dist: geopandas
Requires-Dist: pandas>=2
Requires-Dist: pyogrio
Requires-Dist: rasterio
Requires-Dist: shapely>=2
Requires-Dist: rasterstats
Provides-Extra: tests
Requires-Dist: pytest; extra == "tests"
